nanoemoji/__init__.py
nanoemoji/_version.py
nanoemoji/bitmap_tables.py
nanoemoji/codepoints.py
nanoemoji/color_glyph.py
nanoemoji/colors.py
nanoemoji/colr.py
nanoemoji/colr_to_svg.py
nanoemoji/config.py
nanoemoji/copy.py
nanoemoji/disjoint_set.py
nanoemoji/extract_svgs.py
nanoemoji/extract_svgs_from_otsvg.py
nanoemoji/features.py
nanoemoji/fixed.py
nanoemoji/generate_svgs_from_colr.py
nanoemoji/glue_together.py
nanoemoji/glyph.py
nanoemoji/glyph_reuse.py
nanoemoji/glyphmap.py
nanoemoji/keep_glyph_names.py
nanoemoji/maximum_color.py
nanoemoji/nanoemoji.py
nanoemoji/ninja.py
nanoemoji/paint.py
nanoemoji/parts.py
nanoemoji/png.py
nanoemoji/pngquant.py
nanoemoji/reorder_glyphs.py
nanoemoji/strip_glyph_names.py
nanoemoji/svg.py
nanoemoji/svg_path.py
nanoemoji/util.py
nanoemoji/write_combined_part_files.py
nanoemoji/write_config_for_mergeable.py
nanoemoji/write_diffreport.py
nanoemoji/write_fea.py
nanoemoji/write_font.py
nanoemoji/write_font2png.py
nanoemoji/write_font2png_html.py
nanoemoji/write_glyphgraph.py
nanoemoji/write_glyphmap.py
nanoemoji/write_glyphmap_for_glyph_svgs.py
nanoemoji/write_part_file.py
nanoemoji/write_pngdiff.py
nanoemoji/write_variable_font.py
nanoemoji/data/__init__.py
nanoemoji/data/_default.toml
nanoemoji-0.15.9.dist-info/licenses/LICENSE
nanoemoji-0.15.9.dist-info/METADATA
nanoemoji-0.15.9.dist-info/WHEEL
nanoemoji-0.15.9.dist-info/entry_points.txt
nanoemoji-0.15.9.dist-info/top_level.txt
nanoemoji-0.15.9.dist-info/RECORD
